api/__init__.py
api/temp.py
python_apiy-3.4.29.dist-info/LICENSE
python_apiy-3.4.29.dist-info/METADATA
python_apiy-3.4.29.dist-info/WHEEL
python_apiy-3.4.29.dist-info/top_level.txt
python_apiy-3.4.29.dist-info/RECORD
